[
  { "ch": "一", "pin": "yī", "en": "one", "es": "uno" },
  { "ch": "二", "pin": "èr", "en": "two", "es": "dos" },
  { "ch": "三", "pin": "sān", "en": "three", "es": "tres" },
  { "ch": "四", "pin": "sì", "en": "four", "es": "cuatro" },
  { "ch": "五", "pin": "wǔ", "en": "five", "es": "cinco" },
  { "ch": "六", "pin": "liù", "en": "six", "es": "seis" },
  { "ch": "七", "pin": "qī", "en": "seven", "es": "siete" },
  { "ch": "八", "pin": "bā", "en": "eight", "es": "ocho" },
  { "ch": "九", "pin": "jiǔ", "en": "nine", "es": "nueve" },
  { "ch": "十", "pin": "shí", "en": "ten", "es": "diez" },
  { "ch": "你", "pin": "nǐ", "en": "you", "es": "tú" },
  { "ch": "您", "pin": "nín", "en": "you (formal)", "es": "usted" },
  { "ch": "好", "pin": "hǎo", "en": "good", "es": "bueno" },
  { "ch": "请", "pin": "qǐng", "en": "please", "es": "por favor" },
  { "ch": "问", "pin": "wèn", "en": "to ask", "es": "preguntar" },
  { "ch": "贵", "pin": "guì", "en": "expensive, honorable", "es": "caro, honorable" },
  { "ch": "姓", "pin": "xìng", "en": "surname", "es": "apellido" },
  { "ch": "他", "pin": "tā", "en": "he", "es": "él" },
  { "ch": "她", "pin": "tā", "en": "she", "es": "ella" },
  { "ch": "叫", "pin": "jiào", "en": "to be called", "es": "llamarse" },
  { "ch": "什", "pin": "shén", "en": "what (component)", "es": "qué (componente)" },
  { "ch": "么", "pin": "me", "en": "suffix (what)", "es": "sufijo (qué)" },
  { "ch": "名", "pin": "míng", "en": "name", "es": "nombre" },
  { "ch": "字", "pin": "zì", "en": "character", "es": "carácter" },
  { "ch": "我", "pin": "wǒ", "en": "I, me", "es": "yo" },
  { "ch": "是", "pin": "shì", "en": "to be", "es": "ser" },
  { "ch": "大", "pin": "dà", "en": "big", "es": "grande" },
  { "ch": "学", "pin": "xué", "en": "to study", "es": "estudiar" },
  { "ch": "生", "pin": "shēng", "en": "life", "es": "vida" },
  { "ch": "中", "pin": "zhōng", "en": "middle", "es": "medio" },
  { "ch": "英", "pin": "yīng", "en": "England, heroic", "es": "Inglaterra, héroe" },
  { "ch": "文", "pin": "wén", "en": "language, writing", "es": "lengua, escritura" },
  { "ch": "课", "pin": "kè", "en": "lesson", "es": "lección" },
  { "ch": "老", "pin": "lǎo", "en": "old", "es": "viejo" },
  { "ch": "师", "pin": "shī", "en": "teacher", "es": "maestro" },
  { "ch": "同", "pin": "tóng", "en": "same", "es": "similar, idéntico" },
  { "ch": "校", "pin": "xiào", "en": "school", "es": "colegio" },
  { "ch": "小", "pin": "xiǎo", "en": "small", "es": "pequeño" },
  { "ch": "朋", "pin": "péng", "en": "friend", "es": "amigo" },
  { "ch": "友", "pin": "yǒu", "en": "friend", "es": "amigo" },
  { "ch": "们", "pin": "men", "en": "plural marker", "es": "marcador plural" },
  { "ch": "呢", "pin": "ne", "en": "modal particle", "es": "partícula modal" },
  { "ch": "谢", "pin": "xiè", "en": "to thank", "es": "agradecer" },
  { "ch": "再", "pin": "zài", "en": "again", "es": "otra vez" },
  { "ch": "见", "pin": "jiàn", "en": "to see", "es": "ver" },
  { "ch": "美", "pin": "měi", "en": "beautiful, USA", "es": "bello, EE.UU." },
  { "ch": "国", "pin": "guó", "en": "country", "es": "país" },
  { "ch": "人", "pin": "rén", "en": "person", "es": "persona" },
  { "ch": "吗", "pin": "ma", "en": "(yes/no questions)", "es": "(preguntas sí/no)" },
  { "ch": "也", "pin": "yě", "en": "also", "es": "también" },
  { "ch": "不", "pin": "bù", "en": "not", "es": "no" },
  { "ch": "谁", "pin": "shéi", "en": "who", "es": "quién" },
  { "ch": "的", "pin": "de", "en": "(possessive particle)", "es": "(partícula posesivo)" },
  { "ch": "家", "pin": "jiā", "en": "home, family", "es": "casa, familia" },
  { "ch": "爸", "pin": "bà", "en": "dad", "es": "papá" },
  { "ch": "和", "pin": "hé", "en": "and", "es": "y" },
  { "ch": "妈", "pin": "mā", "en": "mom", "es": "mamá" },
  { "ch": "哥", "pin": "gē", "en": "older brother", "es": "hermano mayor" },
  { "ch": "姐", "pin": "jiě", "en": "older sister", "es": "hermana mayor" },
  { "ch": "弟", "pin": "dì", "en": "younger brother", "es": "hermano menor" },
  { "ch": "妹", "pin": "mèi", "en": "younger sister", "es": "hermana menor" },
  { "ch": "住", "pin": "zhù", "en": "to live", "es": "vivir" },
  { "ch": "在", "pin": "zài", "en": "at, in", "es": "en" },
  { "ch": "这", "pin": "zhè", "en": "this", "es": "este" },
  { "ch": "女", "pin": "nǚ", "en": "female", "es": "mujer" },
  { "ch": "儿", "pin": "ér", "en": "son", "es": "hijo" },
  { "ch": "那", "pin": "nà/nèi", "en": "that", "es": "ese, aquel" },
  { "ch": "男", "pin": "nán", "en": "male", "es": "hombre" },
  { "ch": "孩", "pin": "hái", "en": "child", "es": "niño/a" },
  { "ch": "子", "pin": "zi", "en": "son, (suffix)", "es": "son, (sufijo)" },
  { "ch": "都", "pin": "dōu", "en": "all", "es": "todos" },
  { "ch": "没", "pin": "méi", "en": "not (past)", "es": "no (pasado), no haber" },
  { "ch": "有", "pin": "yǒu", "en": "to have", "es": "tener" },
  { "ch": "做", "pin": "zuò", "en": "to do", "es": "hacer" },
  { "ch": "事", "pin": "shì", "en": "thing", "es": "asunto" },
  { "ch": "两", "pin": "liǎng", "en": "two (counting)", "es": "dos (contar)" },
  { "ch": "个", "pin": "ge", "en": "generic measure word", "es": "clasificador genérico" },
  { "ch": "多", "pin": "duō", "en": "many", "es": "mucho" },
  { "ch": "少", "pin": "shǎo", "en": "few", "es": "poco(s)" },
  { "ch": "时", "pin": "shí", "en": "time", "es": "tiempo" },
  { "ch": "间", "pin": "jiān", "en": "interval", "es": "intervalo" },
  { "ch": "今", "pin": "jīn", "en": "today, now", "es": "hoy, ahora" },
  { "ch": "天", "pin": "tiān", "en": "day, sky", "es": "día, cielo" },
  { "ch": "几", "pin": "jǐ", "en": "how many", "es": "cuántos" },
  { "ch": "号", "pin": "hào", "en": "number", "es": "número" },
  { "ch": "明", "pin": "míng", "en": "bright, next", "es": "brillante, próximo" },
  { "ch": "年", "pin": "nián", "en": "year", "es": "año" },
  { "ch": "月", "pin": "yuè", "en": "month, moon", "es": "mes, luna" },
  { "ch": "日", "pin": "rì", "en": "day, sun", "es": "día, sol" },
  { "ch": "星", "pin": "xīng", "en": "star", "es": "estrella" },
  { "ch": "期", "pin": "qī", "en": "period, week", "es": "periodo, semana" },
  { "ch": "早", "pin": "zǎo", "en": "early", "es": "temprano" },
  { "ch": "上", "pin": "shàng", "en": "up, above", "es": "arriba" },
  { "ch": "下", "pin": "xià", "en": "down, below", "es": "abajo" },
  { "ch": "午", "pin": "wǔ", "en": "noon", "es": "mediodía" },
  { "ch": "吃", "pin": "chī", "en": "to eat", "es": "comer" },
  { "ch": "晚", "pin": "wǎn", "en": "late, evening", "es": "tarde" },
  { "ch": "饭", "pin": "fàn", "en": "meal, rice", "es": "comida, arroz" },
  { "ch": "了", "pin": "le", "en": "(completed action)", "es": "(acción terminada)" },
  { "ch": "哪", "pin": "nǎ", "en": "which", "es": "cuál" }
]
