[
  { "ch": "你好", "pin": "nǐ hǎo", "en": "hello", "es": "hola" },
  { "ch": "你", "pin": "nǐ", "en": "you", "es": "tú" },
  { "ch": "您", "pin": "nín", "en": "you (formal)", "es": "usted" },
  { "ch": "不", "pin": "bù", "en": "not; no", "es": "no" },
  { "ch": "什么", "pin": "shénme", "en": "what", "es": "qué" },
  { "ch": "对不起", "pin": "duìbuqǐ", "en": "sorry", "es": "lo siento" },
  { "ch": "谢谢", "pin": "xièxie", "en": "thank you", "es": "gracias" },
  { "ch": "没关系", "pin": "méi guānxi", "en": "it's okay; no problem", "es": "no pasa nada" },
  { "ch": "你们", "pin": "nǐmen", "en": "you (plural)", "es": "vosotros" },
  { "ch": "中国人", "pin": "Zhōngguórén", "en": "Chinese person", "es": "persona china" },
  { "ch": "再见", "pin": "zài jiàn", "en": "goodbye", "es": "adiós" },
  { "ch": "学生", "pin": "xuésheng", "en": "student", "es": "estudiante" },
  { "ch": "美国", "pin": "Měiguó", "en": "United States", "es": "Estados Unidos" },
  { "ch": "三", "pin": "sān", "en": "three", "es": "tres" },
  { "ch": "十", "pin": "shí", "en": "ten", "es": "diez" },
  { "ch": "八", "pin": "bā", "en": "eight", "es": "ocho" },
  { "ch": "六", "pin": "liù", "en": "six", "es": "seis" },
  { "ch": "口", "pin": "kǒu", "en": "mouth, measure word for family members", "es": "boca, clasificador para familiares" },
  { "ch": "山", "pin": "shān", "en": "mountain", "es": "montaña" },
  { "ch": "小", "pin": "xiǎo", "en": "small", "es": "pequeño" },
  { "ch": "月", "pin": "yuè", "en": "moon, month", "es": "luna, mes" },
  { "ch": "心", "pin": "xīn", "en": "heart", "es": "corazón" },
  { "ch": "中", "pin": "zhōng", "en": "middle, center", "es": "medio, centro" },
  { "ch": "人", "pin": "rén", "en": "person", "es": "persona" }
]
