[
  { "ch": "工作", "pin": "gōngzuò", "en": "work, to work", "es": "trabajo, trabajar" },
  { "ch": "看书", "pin": "kàn shū", "en": "read books", "es": "leer libros" },
  { "ch": "坐", "pin": "zuò", "en": "to sit", "es": "sentarse" },
  { "ch": "桌子", "pin": "zhuōzi", "en": "table, desk", "es": "mesa, escritorio" },
  { "ch": "电脑", "pin": "diànnǎo", "en": "computer", "es": "ordenador" },
  { "ch": "这儿", "pin": "zhèr", "en": "here", "es": "aquí" },
  { "ch": "上", "pin": "shàng", "en": "above, on, up", "es": "arriba, sobre" },
  { "ch": "和", "pin": "hé", "en": "and", "es": "y" },
  { "ch": "前面", "pin": "qiánmiàn", "en": "in front", "es": "delante" },
  { "ch": "后面", "pin": "hòumiàn", "en": "behind", "es": "detrás" },
  { "ch": "能", "pin": "néng", "en": "can, be able to", "es": "poder" },
  { "ch": "里", "pin": "lǐ", "en": "inside", "es": "dentro" },
  { "ch": "本", "pin": "běn", "en": "measure word for books", "es": "clasificador para libros" },
  { "ch": "没有", "pin": "méiyǒu", "en": "not have, there isn't", "es": "no tener, no haber" },
  { "ch": "有", "pin": "yǒu", "en": "to have", "es": "tener" },
  { "ch": "请", "pin": "qǐng", "en": "please, to invite", "es": "por favor, invitar" },
  { "ch": "没", "pin": "méi", "en": "not (past, to have)", "es": "no (pasado, tener)" },
  { "ch": "下面", "pin": "xiàmiàn", "en": "below, under", "es": "debajo" },
  { "ch": "上面", "pin": "shàngmiàn", "en": "above, on top", "es": "encima, sobre" },
  { "ch": "茶", "pin": "chá", "en": "tea", "es": "té" },
  { "ch": "喝", "pin": "hē", "en": "to drink", "es": "beber" },
  { "ch": "医生", "pin": "yīshēng", "en": "doctor", "es": "médico" },
  { "ch": "岁", "pin": "suì", "en": "years old (age)", "es": "años (edad)" },
  { "ch": "朋友", "pin": "péngyou", "en": "friend", "es": "amigo" },
  { "ch": "中国", "pin": "Zhōngguó", "en": "China", "es": "China" },
  { "ch": "家", "pin": "jiā", "en": "home, family", "es": "hogar, familia" },
  { "ch": "名字", "pin": "míngzi", "en": "name", "es": "nombre" },
  { "ch": "您", "pin": "nín", "en": "you (formal)", "es": "usted" }
]
